{
  "ma5": [
    {
      "date": "2025-07-07",
      "prediction": 577.820956785979,
      "actual": 577.0,
      "ma": 575.3891913571958
    },
    {
      "date": "2025-07-08",
      "prediction": 572.6717031481678,
      "actual": 586.5,
      "ma": 575.7735319868294
    },
    {
      "date": "2025-07-09",
      "prediction": 576.5821287913112,
      "actual": 598.25,
      "ma": 576.6399577450916
    },
    {
      "date": "2025-07-10",
      "prediction": 578.2504646160576,
      "actual": 591.0,
      "ma": 576.8150506683031
    },
    {
      "date": "2025-07-11",
      "prediction": 574.4217576835775,
      "actual": 584.25,
      "ma": 575.9494022050187
    },
    {
      "date": "2025-07-14",
      "prediction": 569.1149384918448,
      "actual": 597.0,
      "ma": 574.2081985461917
    },
    {
      "date": "2025-07-15",
      "prediction": 575.9655260355149,
      "actual": 583.75,
      "ma": 574.8669631236611
    },
    {
      "date": "2025-07-16",
      "prediction": 580.9902575431224,
      "actual": null,
      "ma": 575.7485888740235
    },
    {
      "date": "2025-07-17",
      "prediction": 577.4336855928725,
      "actual": null,
      "ma": 575.5852330693864
    },
    {
      "date": "2025-07-18",
      "prediction": 580.0549756206068,
      "actual": null,
      "ma": 576.7118766567924
    },
    {
      "date": "2025-07-21",
      "prediction": 577.392095088028,
      "actual": null,
      "ma": 578.367307976029
    },
    {
      "date": "2025-07-22",
      "prediction": 582.1879031163948,
      "actual": null,
      "ma": 579.6117833922049
    },
    {
      "date": "2025-07-23",
      "prediction": 581.9027434707507,
      "actual": null,
      "ma": 579.7942805777305
    },
    {
      "date": "2025-07-24",
      "prediction": 582.6315238324181,
      "actual": null,
      "ma": 580.8338482256397
    },
    {
      "date": "2025-07-25",
      "prediction": 582.7855639987664,
      "actual": null,
      "ma": 581.3799659012716
    },
    {
      "date": "2025-07-28",
      "prediction": 585.7475016855582,
      "actual": null,
      "ma": 583.0510472207776
    },
    {
      "date": "2025-07-29",
      "prediction": 577.9833739986833,
      "actual": null,
      "ma": 582.2101413972352
    },
    {
      "date": "2025-07-30",
      "prediction": 579.7153141632177,
      "actual": null,
      "ma": 581.7726555357287
    },
    {
      "date": "2025-07-31",
      "prediction": 577.2703841993621,
      "actual": null,
      "ma": 580.7004276091176
    },
    {
      "date": "2025-08-01",
      "prediction": 576.9376828319088,
      "actual": null,
      "ma": 579.530851375746
    },
    {
      "date": "2025-08-04",
      "prediction": 571.1798520794651,
      "actual": null,
      "ma": 576.6173214545274
    },
    {
      "date": "2025-08-05",
      "prediction": 579.0446290147768,
      "actual": null,
      "ma": 576.8295724577462
    },
    {
      "date": "2025-08-06",
      "prediction": 575.3745758587492,
      "actual": null,
      "ma": 575.9614247968524
    }
  ],
  "ma10": [
    {
      "date": "2025-07-07",
      "prediction": 577.820956785979,
      "actual": 577.0,
      "ma": 575.369595678598
    },
    {
      "date": "2025-07-08",
      "prediction": 572.6717031481678,
      "actual": 586.5,
      "ma": 574.0117659934147
    },
    {
      "date": "2025-07-09",
      "prediction": 576.5821287913112,
      "actual": 598.25,
      "ma": 573.7449788725459
    },
    {
      "date": "2025-07-10",
      "prediction": 578.2504646160576,
      "actual": 591.0,
      "ma": 574.6950253341515
    },
    {
      "date": "2025-07-11",
      "prediction": 574.4217576835775,
      "actual": 584.25,
      "ma": 575.1622011025094
    },
    {
      "date": "2025-07-14",
      "prediction": 569.1149384918448,
      "actual": 597.0,
      "ma": 574.7986949516937
    },
    {
      "date": "2025-07-15",
      "prediction": 575.9655260355149,
      "actual": 583.75,
      "ma": 575.3202475552453
    },
    {
      "date": "2025-07-16",
      "prediction": 580.9902575431224,
      "actual": null,
      "ma": 576.1942733095575
    },
    {
      "date": "2025-07-17",
      "prediction": 577.4336855928725,
      "actual": null,
      "ma": 576.2001418688448
    },
    {
      "date": "2025-07-18",
      "prediction": 580.0549756206068,
      "actual": null,
      "ma": 576.3306394309054
    },
    {
      "date": "2025-07-21",
      "prediction": 577.392095088028,
      "actual": null,
      "ma": 576.2877532611103
    },
    {
      "date": "2025-07-22",
      "prediction": 582.1879031163948,
      "actual": null,
      "ma": 577.239373257933
    },
    {
      "date": "2025-07-23",
      "prediction": 581.9027434707507,
      "actual": null,
      "ma": 577.7714347258769
    },
    {
      "date": "2025-07-24",
      "prediction": 582.6315238324181,
      "actual": null,
      "ma": 578.2095406475131
    },
    {
      "date": "2025-07-25",
      "prediction": 582.7855639987664,
      "actual": null,
      "ma": 579.0459212790319
    },
    {
      "date": "2025-07-28",
      "prediction": 585.7475016855582,
      "actual": null,
      "ma": 580.7091775984034
    },
    {
      "date": "2025-07-29",
      "prediction": 577.9833739986833,
      "actual": null,
      "ma": 580.9109623947202
    },
    {
      "date": "2025-07-30",
      "prediction": 579.7153141632177,
      "actual": null,
      "ma": 580.7834680567296
    },
    {
      "date": "2025-07-31",
      "prediction": 577.2703841993621,
      "actual": null,
      "ma": 580.7671379173786
    },
    {
      "date": "2025-08-01",
      "prediction": 576.9376828319088,
      "actual": null,
      "ma": 580.4554086385087
    },
    {
      "date": "2025-08-04",
      "prediction": 571.1798520794651,
      "actual": null,
      "ma": 579.8341843376526
    },
    {
      "date": "2025-08-05",
      "prediction": 579.0446290147768,
      "actual": null,
      "ma": 579.5198569274907
    },
    {
      "date": "2025-08-06",
      "prediction": 575.3745758587492,
      "actual": null,
      "ma": 578.8670401662905
    }
  ],
  "ma23": [
    {
      "date": "2025-07-07",
      "prediction": 577.820956785979,
      "actual": 577.0,
      "ma": 591.4215633385209
    },
    {
      "date": "2025-07-08",
      "prediction": 572.6717031481678,
      "actual": 586.5,
      "ma": 592.0975069536586
    },
    {
      "date": "2025-07-09",
      "prediction": 576.5821287913112,
      "actual": 598.25,
      "ma": 592.7967299445852
    },
    {
      "date": "2025-07-10",
      "prediction": 578.2504646160576,
      "actual": 591.0,
      "ma": 593.2478371018051
    },
    {
      "date": "2025-07-11",
      "prediction": 574.4217576835775,
      "actual": 584.25,
      "ma": 593.2879135228301
    },
    {
      "date": "2025-07-14",
      "prediction": 569.1149384918448,
      "actual": 597.0,
      "ma": 593.1842151963887
    },
    {
      "date": "2025-07-15",
      "prediction": 575.9655260355149,
      "actual": 583.75,
      "ma": 592.8131511109762
    },
    {
      "date": "2025-07-16",
      "prediction": 580.9902575431224,
      "actual": null,
      "ma": 591.0953362215467
    },
    {
      "date": "2025-07-17",
      "prediction": 577.4336855928725,
      "actual": null,
      "ma": 589.0652790734108
    },
    {
      "date": "2025-07-18",
      "prediction": 580.0549756206068,
      "actual": null,
      "ma": 587.0839736656111
    },
    {
      "date": "2025-07-21",
      "prediction": 577.392095088028,
      "actual": null,
      "ma": 584.6608038868296
    },
    {
      "date": "2025-07-22",
      "prediction": 582.1879031163948,
      "actual": null,
      "ma": 582.0331040223251
    },
    {
      "date": "2025-07-23",
      "prediction": 581.9027434707507,
      "actual": null,
      "ma": 579.2353972167056
    },
    {
      "date": "2025-07-24",
      "prediction": 582.6315238324181,
      "actual": null,
      "ma": 576.6650286876802
    },
    {
      "date": "2025-07-25",
      "prediction": 582.7855639987664,
      "actual": null,
      "ma": 576.5144010354527
    },
    {
      "date": "2025-07-28",
      "prediction": 585.7475016855582,
      "actual": null,
      "ma": 576.7969011087379
    },
    {
      "date": "2025-07-29",
      "prediction": 577.9833739986833,
      "actual": null,
      "ma": 577.1983521521588
    },
    {
      "date": "2025-07-30",
      "prediction": 579.7153141632177,
      "actual": null,
      "ma": 577.6316266809945
    },
    {
      "date": "2025-07-31",
      "prediction": 577.2703841993621,
      "actual": null,
      "ma": 577.8281651244449
    },
    {
      "date": "2025-08-01",
      "prediction": 576.9376828319088,
      "actual": null,
      "ma": 578.0971948127888
    },
    {
      "date": "2025-08-04",
      "prediction": 571.1798520794651,
      "actual": null,
      "ma": 578.0506666423307
    },
    {
      "date": "2025-08-05",
      "prediction": 579.0446290147768,
      "actual": null,
      "ma": 578.1232592081907
    },
    {
      "date": "2025-08-06",
      "prediction": 575.3745758587492,
      "actual": null,
      "ma": 577.9765016368319
    }
  ]
}